pt_exporter/__init__.py
pt_exporter/__main__.py
pt_exporter/configuration.py
pt_exporter/crawlers.py
pt_exporter-1.0.7.dist-info/METADATA
pt_exporter-1.0.7.dist-info/WHEEL
pt_exporter-1.0.7.dist-info/entry_points.txt
pt_exporter-1.0.7.dist-info/top_level.txt
pt_exporter-1.0.7.dist-info/RECORD
