Metadata-Version: 2.1
Name: pt-exporter
Version: 1.0.7
Summary: a prometheus exporter for private tracker
Home-page: https://github.com/zqmillet/pt-exporter
Author: kinopico
Author-email: zqmillet@qq.com
License: UNKNOWN
Platform: UNKNOWN
Requires-Dist: APScheduler (==3.9.1)
Requires-Dist: fastapi
Requires-Dist: loguru (==0.7.2)
Requires-Dist: prometheus-client (==0.21.0)
Requires-Dist: pydantic
Requires-Dist: PyYAML (==6.0.2)
Requires-Dist: uvicorn (==0.32.0)
Requires-Dist: pt-crawler
